marv_robotics/__init__.py
marv_robotics/bag.capnp
marv_robotics/bag.py
marv_robotics/cam.py
marv_robotics/detail.py
marv_robotics/fulltext.py
marv_robotics/gnss.py
marv_robotics/matplotlibrc
marv_robotics/motion.py
marv_robotics/trajectory.py
marv_robotics/tests/__init__.py
marv_robotics/tests/test_bag_scan.py
marv_robotics/tests/test_bag_utils.py
marv_ros/__init__.py
marv_ros/img_tools.py
marv_robotics-21.12.0.dist-info/LICENSE.txt
marv_robotics-21.12.0.dist-info/METADATA
marv_robotics-21.12.0.dist-info/WHEEL
marv_robotics-21.12.0.dist-info/top_level.txt
marv_robotics-21.12.0.dist-info/RECORD
