Metadata-Version: 2.1
Name: marv-robotics
Version: 21.12.0
Summary: Data management platform for robot logs
Home-page: https://ternaris.com/marv-robotics
Author: Ternaris
Author-email: team@ternaris.com
Maintainer: Ternaris
Maintainer-email: team@ternaris.com
License: AGPL-3.0-only
Project-URL: Documentation, https://ternaris.com/marv-robotics/docs/
Project-URL: Code, https://gitlab.com/ternaris/marv-robotics
Project-URL: Issue tracker, https://gitlab.com/ternaris/marv-robotics/issues
Platform: UNKNOWN
Classifier: Development Status :: 5 - Production/Stable
Classifier: License :: OSI Approved :: GNU Affero General Public License v3
Classifier: Operating System :: POSIX :: Linux
Classifier: Programming Language :: Python :: 3 :: Only
Classifier: Programming Language :: Python :: 3.8
Classifier: Programming Language :: Python :: Implementation :: CPython
Classifier: Programming Language :: Python
Classifier: Topic :: Scientific/Engineering
Requires-Python: >=3.8.2
Requires-Dist: marv-api (==21.12.0)
Requires-Dist: lz4
Requires-Dist: matplotlib (==3.2.*)
Requires-Dist: mpld3
Requires-Dist: numpy
Requires-Dist: pillow
Requires-Dist: plotly
Requires-Dist: pycryptodome
Requires-Dist: rosbags
Requires-Dist: ruamel.yaml
Requires-Dist: utm
Requires-Dist: zstandard
